<SceneObjectGroup><SceneObjectPart xmlns:xsi="http://www.w3.org/2001/XMLSchema-instance" xmlns:xsd="http://www.w3.org/2001/XMLSchema"><AllowedDrop>false</AllowedDrop><CreatorID><Guid>d5f1046f-7582-40e3-951c-b902143a2c9c</Guid></CreatorID><FolderID><Guid>76d2da76-844c-4ccf-a8c7-2203f9757f29</Guid></FolderID><InventorySerial>8</InventorySerial><TaskInventory /><ObjectFlags>1024</ObjectFlags><UUID><Guid>76d2da76-844c-4ccf-a8c7-2203f9757f29</Guid></UUID><LocalId>1082081615</LocalId><Name>Primitive</Name><Material>3</Material><PassTouches>false</PassTouches><RegionHandle>11576757931588352</RegionHandle><ScriptAccessPin>0</ScriptAccessPin><PlaySoundSlavePrims /><LoopSoundSlavePrims /><GroupPosition><X>194.111954</X><Y>85.82587</Y><Z>61.5894661</Z></GroupPosition><OffsetPosition><X>0</X><Y>0</Y><Z>0</Z></OffsetPosition><RotationOffset><X>0.312938958</X><Y>-0.212886542</Y><Z>0.9084192</Z><W>0.177547455</W></RotationOffset><Velocity><X>0</X><Y>0</Y><Z>0</Z></Velocity><AngularVelocity><X>0</X><Y>0</Y><Z>0</Z></AngularVelocity><Acceleration><X>0</X><Y>0</Y><Z>0</Z></Acceleration><Description /><Color /><Text /><SitName>Sit here</SitName><TouchName /><LinkNum>1</LinkNum><ClickAction>0</ClickAction><Shape><ProfileCurve>1</ProfileCurve><TextureEntry>ZFmkkrLWSzuwoLs/7GrGDAQLOj7sj9BFI5dQdmLWbRpWEAs6PuyP0EUjl1B2YtZtGlYACRxy/wCamZk+AJqZmT4AAAAAAAAAAAAAIAAAAAA=</TextureEntry><ExtraParams>AA==</ExtraParams><PathBegin>0</PathBegin><PathCurve>16</PathCurve><PathEnd>0</PathEnd><PathRadiusOffset>0</PathRadiusOffset><PathRevolutions>0</PathRevolutions><PathScaleX>100</PathScaleX><PathScaleY>100</PathScaleY><PathShearX>0</PathShearX><PathShearY>0</PathShearY><PathSkew>0</PathSkew><PathTaperX>0</PathTaperX><PathTaperY>0</PathTaperY><PathTwist>0</PathTwist><PathTwistBegin>0</PathTwistBegin><PCode>9</PCode><ProfileBegin>0</ProfileBegin><ProfileEnd>0</ProfileEnd><ProfileHollow>0</ProfileHollow><Scale><X>0.5</X><Y>5.25640869</Y><Z>10</Z></Scale><State>0</State><ProfileShape>Square</ProfileShape><HollowShape>Same</HollowShape><SculptTexture><Guid>00000000-0000-0000-0000-000000000000</Guid></SculptTexture><SculptType>0</SculptType><SculptData /><FlexiSoftness>0</FlexiSoftness><FlexiTension>0</FlexiTension><FlexiDrag>0</FlexiDrag><FlexiGravity>0</FlexiGravity><FlexiWind>0</FlexiWind><FlexiForceX>0</FlexiForceX><FlexiForceY>0</FlexiForceY><FlexiForceZ>0</FlexiForceZ><LightColorR>0</LightColorR><LightColorG>0</LightColorG><LightColorB>0</LightColorB><LightColorA>1</LightColorA><LightRadius>0</LightRadius><LightCutoff>0</LightCutoff><LightFalloff>0</LightFalloff><LightIntensity>1</LightIntensity><FlexiEntry>false</FlexiEntry><LightEntry>false</LightEntry><SculptEntry>false</SculptEntry></Shape><Scale><X>0.5</X><Y>5.25640869</Y><Z>10</Z></Scale><UpdateFlag>0</UpdateFlag><SitTargetOrientation><X>0</X><Y>0</Y><Z>0</Z><W>1</W></SitTargetOrientation><SitTargetPosition><X>0</X><Y>0</Y><Z>0.5</Z></SitTargetPosition><SitTargetPositionLL><X>0</X><Y>0</Y><Z>0.5</Z></SitTargetPositionLL><SitTargetOrientationLL><X>0</X><Y>0</Y><Z>0</Z><W>1</W></SitTargetOrientationLL><ParentID>0</ParentID><CreationDate>1292715183</CreationDate><Category>0</Category><SalePrice>0</SalePrice><ObjectSaleType>0</ObjectSaleType><OwnershipCost>0</OwnershipCost><GroupID><Guid>00000000-0000-0000-0000-000000000000</Guid></GroupID><OwnerID><Guid>d5f1046f-7582-40e3-951c-b902143a2c9c</Guid></OwnerID><LastOwnerID><Guid>d5f1046f-7582-40e3-951c-b902143a2c9c</Guid></LastOwnerID><BaseMask>2147483647</BaseMask><OwnerMask>2147483647</OwnerMask><GroupMask>0</GroupMask><EveryoneMask>0</EveryoneMask><NextOwnerMask>2147483647</NextOwnerMask><Flags>Phantom</Flags><CollisionSound><Guid>00000000-0000-0000-0000-000000000000</Guid></CollisionSound><CollisionSoundVolume>0</CollisionSoundVolume></SceneObjectPart><OtherParts><SceneObjectPart xmlns:xsi="http://www.w3.org/2001/XMLSchema-instance" xmlns:xsd="http://www.w3.org/2001/XMLSchema"><AllowedDrop>false</AllowedDrop><CreatorID><Guid>d5f1046f-7582-40e3-951c-b902143a2c9c</Guid></CreatorID><FolderID><Guid>0d45169c-877a-40b8-b383-136d391c12e4</Guid></FolderID><InventorySerial>0</InventorySerial><TaskInventory /><ObjectFlags>1088</ObjectFlags><UUID><Guid>0d45169c-877a-40b8-b383-136d391c12e4</Guid></UUID><LocalId>1082081606</LocalId><Name>Primitive</Name><Material>3</Material><PassTouches>false</PassTouches><RegionHandle>11576757931588352</RegionHandle><ScriptAccessPin>0</ScriptAccessPin><PlaySoundSlavePrims /><LoopSoundSlavePrims /><GroupPosition><X>194.111954</X><Y>85.82587</Y><Z>61.5894661</Z></GroupPosition><OffsetPosition><X>1.04009271</X><Y>0.06279317</Y><Z>-0.0565751828</Z></OffsetPosition><RotationOffset><X>-0.0158962663</X><Y>0.1207814</Y><Z>0.09811769</Z><W>0.98769027</W></RotationOffset><Velocity><X>0</X><Y>0</Y><Z>0</Z></Velocity><AngularVelocity><X>0</X><Y>0</Y><Z>0</Z></AngularVelocity><Acceleration><X>0</X><Y>0</Y><Z>0</Z></Acceleration><Description /><Color /><Text /><SitName /><TouchName /><LinkNum>10</LinkNum><ClickAction>0</ClickAction><Shape><ProfileCurve>1</ProfileCurve><TextureEntry>ZFmkkrLWSzuwoLs/7GrGDBQLOj7sj9BFI5dQdmLWbRpWAAkcctsAmpmZPgCamZk+AAAAAAAAAAAAACAAAAAA</TextureEntry><ExtraParams>AA==</ExtraParams><PathBegin>0</PathBegin><PathCurve>16</PathCurve><PathEnd>0</PathEnd><PathRadiusOffset>0</PathRadiusOffset><PathRevolutions>0</PathRevolutions><PathScaleX>100</PathScaleX><PathScaleY>100</PathScaleY><PathShearX>0</PathShearX><PathShearY>0</PathShearY><PathSkew>0</PathSkew><PathTaperX>0</PathTaperX><PathTaperY>0</PathTaperY><PathTwist>0</PathTwist><PathTwistBegin>0</PathTwistBegin><PCode>9</PCode><ProfileBegin>0</ProfileBegin><ProfileEnd>0</ProfileEnd><ProfileHollow>0</ProfileHollow><Scale><X>0.5</X><Y>5.25640869</Y><Z>10</Z></Scale><State>0</State><ProfileShape>Square</ProfileShape><HollowShape>Same</HollowShape><SculptTexture><Guid>00000000-0000-0000-0000-000000000000</Guid></SculptTexture><SculptType>0</SculptType><SculptData /><FlexiSoftness>0</FlexiSoftness><FlexiTension>0</FlexiTension><FlexiDrag>0</FlexiDrag><FlexiGravity>0</FlexiGravity><FlexiWind>0</FlexiWind><FlexiForceX>0</FlexiForceX><FlexiForceY>0</FlexiForceY><FlexiForceZ>0</FlexiForceZ><LightColorR>0</LightColorR><LightColorG>0</LightColorG><LightColorB>0</LightColorB><LightColorA>1</LightColorA><LightRadius>0</LightRadius><LightCutoff>0</LightCutoff><LightFalloff>0</LightFalloff><LightIntensity>1</LightIntensity><FlexiEntry>false</FlexiEntry><LightEntry>false</LightEntry><SculptEntry>false</SculptEntry></Shape><Scale><X>0.5</X><Y>5.25640869</Y><Z>10</Z></Scale><UpdateFlag>0</UpdateFlag><SitTargetOrientation><X>0</X><Y>0</Y><Z>0</Z><W>1</W></SitTargetOrientation><SitTargetPosition><X>0</X><Y>0</Y><Z>0</Z></SitTargetPosition><SitTargetPositionLL><X>0</X><Y>0</Y><Z>0</Z></SitTargetPositionLL><SitTargetOrientationLL><X>0</X><Y>0</Y><Z>0</Z><W>1</W></SitTargetOrientationLL><ParentID>1082081615</ParentID><CreationDate>1292715182</CreationDate><Category>0</Category><SalePrice>10</SalePrice><ObjectSaleType>0</ObjectSaleType><OwnershipCost>0</OwnershipCost><GroupID><Guid>00000000-0000-0000-0000-000000000000</Guid></GroupID><OwnerID><Guid>d5f1046f-7582-40e3-951c-b902143a2c9c</Guid></OwnerID><LastOwnerID><Guid>d5f1046f-7582-40e3-951c-b902143a2c9c</Guid></LastOwnerID><BaseMask>2147483647</BaseMask><OwnerMask>2147483647</OwnerMask><GroupMask>0</GroupMask><EveryoneMask>0</EveryoneMask><NextOwnerMask>2147483647</NextOwnerMask><Flags>Scripted Phantom</Flags><CollisionSound><Guid>00000000-0000-0000-0000-000000000000</Guid></CollisionSound><CollisionSoundVolume>0</CollisionSoundVolume></SceneObjectPart><SceneObjectPart xmlns:xsi="http://www.w3.org/2001/XMLSchema-instance" xmlns:xsd="http://www.w3.org/2001/XMLSchema"><AllowedDrop>false</AllowedDrop><CreatorID><Guid>d5f1046f-7582-40e3-951c-b902143a2c9c</Guid></CreatorID><FolderID><Guid>4bd43570-f16e-4d73-aa64-16e5a52f905c</Guid></FolderID><InventorySerial>0</InventorySerial><TaskInventory /><ObjectFlags>1088</ObjectFlags><UUID><Guid>4bd43570-f16e-4d73-aa64-16e5a52f905c</Guid></UUID><LocalId>1082081607</LocalId><Name>Primitive</Name><Material>3</Material><PassTouches>false</PassTouches><RegionHandle>11576757931588352</RegionHandle><ScriptAccessPin>0</ScriptAccessPin><PlaySoundSlavePrims /><LoopSoundSlavePrims /><GroupPosition><X>194.111954</X><Y>85.82587</Y><Z>61.5894661</Z></GroupPosition><OffsetPosition><X>1.17273092</X><Y>-0.07803889</Y><Z>-2.22731662</Z></OffsetPosition><RotationOffset><X>0.182388023</X><Y>0.182722926</Y><Z>-0.610161066</Z><W>0.749033</W></RotationOffset><Velocity><X>0</X><Y>0</Y><Z>0</Z></Velocity><AngularVelocity><X>0</X><Y>0</Y><Z>0</Z></AngularVelocity><Acceleration><X>0</X><Y>0</Y><Z>0</Z></Acceleration><Description /><Color /><Text /><SitName /><TouchName /><LinkNum>9</LinkNum><ClickAction>0</ClickAction><Shape><ProfileCurve>1</ProfileCurve><TextureEntry>ZFmkkrLWSzuwoLs/7GrGDBQLOj7sj9BFI5dQdmLWbRpWAAkcctsAmpmZPgCamZk+AAAAAAAAAAAAACAAAAAA</TextureEntry><ExtraParams>AA==</ExtraParams><PathBegin>0</PathBegin><PathCurve>16</PathCurve><PathEnd>0</PathEnd><PathRadiusOffset>0</PathRadiusOffset><PathRevolutions>0</PathRevolutions><PathScaleX>100</PathScaleX><PathScaleY>100</PathScaleY><PathShearX>0</PathShearX><PathShearY>0</PathShearY><PathSkew>0</PathSkew><PathTaperX>0</PathTaperX><PathTaperY>0</PathTaperY><PathTwist>0</PathTwist><PathTwistBegin>0</PathTwistBegin><PCode>9</PCode><ProfileBegin>0</ProfileBegin><ProfileEnd>0</ProfileEnd><ProfileHollow>0</ProfileHollow><Scale><X>0.5</X><Y>5.25640869</Y><Z>10</Z></Scale><State>0</State><ProfileShape>Square</ProfileShape><HollowShape>Same</HollowShape><SculptTexture><Guid>00000000-0000-0000-0000-000000000000</Guid></SculptTexture><SculptType>0</SculptType><SculptData /><FlexiSoftness>0</FlexiSoftness><FlexiTension>0</FlexiTension><FlexiDrag>0</FlexiDrag><FlexiGravity>0</FlexiGravity><FlexiWind>0</FlexiWind><FlexiForceX>0</FlexiForceX><FlexiForceY>0</FlexiForceY><FlexiForceZ>0</FlexiForceZ><LightColorR>0</LightColorR><LightColorG>0</LightColorG><LightColorB>0</LightColorB><LightColorA>1</LightColorA><LightRadius>0</LightRadius><LightCutoff>0</LightCutoff><LightFalloff>0</LightFalloff><LightIntensity>1</LightIntensity><FlexiEntry>false</FlexiEntry><LightEntry>false</LightEntry><SculptEntry>false</SculptEntry></Shape><Scale><X>0.5</X><Y>5.25640869</Y><Z>10</Z></Scale><UpdateFlag>0</UpdateFlag><SitTargetOrientation><X>0</X><Y>0</Y><Z>0</Z><W>1</W></SitTargetOrientation><SitTargetPosition><X>0</X><Y>0</Y><Z>0</Z></SitTargetPosition><SitTargetPositionLL><X>0</X><Y>0</Y><Z>0</Z></SitTargetPositionLL><SitTargetOrientationLL><X>0</X><Y>0</Y><Z>0</Z><W>1</W></SitTargetOrientationLL><ParentID>1082081615</ParentID><CreationDate>1292715182</CreationDate><Category>0</Category><SalePrice>10</SalePrice><ObjectSaleType>0</ObjectSaleType><OwnershipCost>0</OwnershipCost><GroupID><Guid>00000000-0000-0000-0000-000000000000</Guid></GroupID><OwnerID><Guid>d5f1046f-7582-40e3-951c-b902143a2c9c</Guid></OwnerID><LastOwnerID><Guid>d5f1046f-7582-40e3-951c-b902143a2c9c</Guid></LastOwnerID><BaseMask>2147483647</BaseMask><OwnerMask>2147483647</OwnerMask><GroupMask>0</GroupMask><EveryoneMask>0</EveryoneMask><NextOwnerMask>2147483647</NextOwnerMask><Flags>Scripted Phantom</Flags><CollisionSound><Guid>00000000-0000-0000-0000-000000000000</Guid></CollisionSound><CollisionSoundVolume>0</CollisionSoundVolume></SceneObjectPart><SceneObjectPart xmlns:xsi="http://www.w3.org/2001/XMLSchema-instance" xmlns:xsd="http://www.w3.org/2001/XMLSchema"><AllowedDrop>false</AllowedDrop><CreatorID><Guid>d5f1046f-7582-40e3-951c-b902143a2c9c</Guid></CreatorID><FolderID><Guid>79fe1735-1c0c-41f5-89e6-ac76bfc51416</Guid></FolderID><InventorySerial>0</InventorySerial><TaskInventory /><ObjectFlags>1088</ObjectFlags><UUID><Guid>79fe1735-1c0c-41f5-89e6-ac76bfc51416</Guid></UUID><LocalId>1082081608</LocalId><Name>Primitive</Name><Material>3</Material><PassTouches>false</PassTouches><RegionHandle>11576757931588352</RegionHandle><ScriptAccessPin>0</ScriptAccessPin><PlaySoundSlavePrims /><LoopSoundSlavePrims /><GroupPosition><X>194.111954</X><Y>85.82587</Y><Z>61.5894661</Z></GroupPosition><OffsetPosition><X>0.385142326</X><Y>0.268920243</Y><Z>-2.893065</Z></OffsetPosition><RotationOffset><X>-0.30516988</X><Y>0.21367541</Y><Z>-0.9113592</Z><W>0.175038621</W></RotationOffset><Velocity><X>0</X><Y>0</Y><Z>0</Z></Velocity><AngularVelocity><X>0</X><Y>0</Y><Z>0</Z></AngularVelocity><Acceleration><X>0</X><Y>0</Y><Z>0</Z></Acceleration><Description /><Color /><Text /><SitName /><TouchName /><LinkNum>8</LinkNum><ClickAction>0</ClickAction><Shape><ProfileCurve>1</ProfileCurve><TextureEntry>ZFmkkrLWSzuwoLs/7GrGDAAAAADbAAAAgD8AAACAPwAAAAAAAAAAAAAAAAAAAA==</TextureEntry><ExtraParams>ASAAEAAAAP////8AACBBAAAAAAAAQD8=</ExtraParams><PathBegin>0</PathBegin><PathCurve>16</PathCurve><PathEnd>0</PathEnd><PathRadiusOffset>0</PathRadiusOffset><PathRevolutions>0</PathRevolutions><PathScaleX>100</PathScaleX><PathScaleY>100</PathScaleY><PathShearX>0</PathShearX><PathShearY>0</PathShearY><PathSkew>0</PathSkew><PathTaperX>0</PathTaperX><PathTaperY>0</PathTaperY><PathTwist>0</PathTwist><PathTwistBegin>0</PathTwistBegin><PCode>9</PCode><ProfileBegin>0</ProfileBegin><ProfileEnd>0</ProfileEnd><ProfileHollow>0</ProfileHollow><Scale><X>0.51</X><Y>10</Y><Z>0.5</Z></Scale><State>0</State><ProfileShape>Square</ProfileShape><HollowShape>Same</HollowShape><SculptTexture><Guid>00000000-0000-0000-0000-000000000000</Guid></SculptTexture><SculptType>0</SculptType><SculptData /><FlexiSoftness>0</FlexiSoftness><FlexiTension>0</FlexiTension><FlexiDrag>0</FlexiDrag><FlexiGravity>0</FlexiGravity><FlexiWind>0</FlexiWind><FlexiForceX>0</FlexiForceX><FlexiForceY>0</FlexiForceY><FlexiForceZ>0</FlexiForceZ><LightColorR>1</LightColorR><LightColorG>1</LightColorG><LightColorB>1</LightColorB><LightColorA>1</LightColorA><LightRadius>10</LightRadius><LightCutoff>0</LightCutoff><LightFalloff>0.75</LightFalloff><LightIntensity>1</LightIntensity><FlexiEntry>false</FlexiEntry><LightEntry>true</LightEntry><SculptEntry>false</SculptEntry></Shape><Scale><X>0.51</X><Y>10</Y><Z>0.5</Z></Scale><UpdateFlag>0</UpdateFlag><SitTargetOrientation><X>0</X><Y>0</Y><Z>0</Z><W>1</W></SitTargetOrientation><SitTargetPosition><X>0</X><Y>0</Y><Z>0</Z></SitTargetPosition><SitTargetPositionLL><X>0</X><Y>0</Y><Z>0</Z></SitTargetPositionLL><SitTargetOrientationLL><X>0</X><Y>0</Y><Z>0</Z><W>1</W></SitTargetOrientationLL><ParentID>1082081615</ParentID><CreationDate>1292715182</CreationDate><Category>0</Category><SalePrice>10</SalePrice><ObjectSaleType>0</ObjectSaleType><OwnershipCost>0</OwnershipCost><GroupID><Guid>00000000-0000-0000-0000-000000000000</Guid></GroupID><OwnerID><Guid>d5f1046f-7582-40e3-951c-b902143a2c9c</Guid></OwnerID><LastOwnerID><Guid>d5f1046f-7582-40e3-951c-b902143a2c9c</Guid></LastOwnerID><BaseMask>2147483647</BaseMask><OwnerMask>2147483647</OwnerMask><GroupMask>0</GroupMask><EveryoneMask>0</EveryoneMask><NextOwnerMask>2147483647</NextOwnerMask><Flags>Scripted Phantom</Flags><CollisionSound><Guid>00000000-0000-0000-0000-000000000000</Guid></CollisionSound><CollisionSoundVolume>0</CollisionSoundVolume></SceneObjectPart><SceneObjectPart xmlns:xsi="http://www.w3.org/2001/XMLSchema-instance" xmlns:xsd="http://www.w3.org/2001/XMLSchema"><AllowedDrop>false</AllowedDrop><CreatorID><Guid>d5f1046f-7582-40e3-951c-b902143a2c9c</Guid></CreatorID><FolderID><Guid>41d06c38-54b0-49ae-ab42-c7725dff5d1d</Guid></FolderID><InventorySerial>0</InventorySerial><TaskInventory /><ObjectFlags>1088</ObjectFlags><UUID><Guid>41d06c38-54b0-49ae-ab42-c7725dff5d1d</Guid></UUID><LocalId>1082081609</LocalId><Name>Primitive</Name><Material>3</Material><PassTouches>false</PassTouches><RegionHandle>11576757931588352</RegionHandle><ScriptAccessPin>0</ScriptAccessPin><PlaySoundSlavePrims /><LoopSoundSlavePrims /><GroupPosition><X>194.111954</X><Y>85.82587</Y><Z>61.5894661</Z></GroupPosition><OffsetPosition><X>1.25318956</X><Y>-0.6056666</Y><Z>-2.16274047</Z></OffsetPosition><RotationOffset><X>0.324920446</X><Y>0.357730329</Y><Z>-0.5409994</Z><W>0.6883134</W></RotationOffset><Velocity><X>0</X><Y>0</Y><Z>0</Z></Velocity><AngularVelocity><X>0</X><Y>0</Y><Z>0</Z></AngularVelocity><Acceleration><X>0</X><Y>0</Y><Z>0</Z></Acceleration><Description /><Color /><Text /><SitName /><TouchName /><LinkNum>7</LinkNum><ClickAction>0</ClickAction><Shape><ProfileCurve>1</ProfileCurve><TextureEntry>ZFmkkrLWSzuwoLs/7GrGDBQLOj7sj9BFI5dQdmLWbRpWAAkcctsAmpmZPgCamZk+AAAAAAAAAAAAACAAAAAA</TextureEntry><ExtraParams>AA==</ExtraParams><PathBegin>0</PathBegin><PathCurve>16</PathCurve><PathEnd>0</PathEnd><PathRadiusOffset>0</PathRadiusOffset><PathRevolutions>0</PathRevolutions><PathScaleX>100</PathScaleX><PathScaleY>100</PathScaleY><PathShearX>0</PathShearX><PathShearY>0</PathShearY><PathSkew>0</PathSkew><PathTaperX>0</PathTaperX><PathTaperY>0</PathTaperY><PathTwist>0</PathTwist><PathTwistBegin>0</PathTwistBegin><PCode>9</PCode><ProfileBegin>0</ProfileBegin><ProfileEnd>0</ProfileEnd><ProfileHollow>0</ProfileHollow><Scale><X>0.5</X><Y>5.25640869</Y><Z>10</Z></Scale><State>0</State><ProfileShape>Square</ProfileShape><HollowShape>Same</HollowShape><SculptTexture><Guid>00000000-0000-0000-0000-000000000000</Guid></SculptTexture><SculptType>0</SculptType><SculptData /><FlexiSoftness>0</FlexiSoftness><FlexiTension>0</FlexiTension><FlexiDrag>0</FlexiDrag><FlexiGravity>0</FlexiGravity><FlexiWind>0</FlexiWind><FlexiForceX>0</FlexiForceX><FlexiForceY>0</FlexiForceY><FlexiForceZ>0</FlexiForceZ><LightColorR>0</LightColorR><LightColorG>0</LightColorG><LightColorB>0</LightColorB><LightColorA>1</LightColorA><LightRadius>0</LightRadius><LightCutoff>0</LightCutoff><LightFalloff>0</LightFalloff><LightIntensity>1</LightIntensity><FlexiEntry>false</FlexiEntry><LightEntry>false</LightEntry><SculptEntry>false</SculptEntry></Shape><Scale><X>0.5</X><Y>5.25640869</Y><Z>10</Z></Scale><UpdateFlag>0</UpdateFlag><SitTargetOrientation><X>0</X><Y>0</Y><Z>0</Z><W>1</W></SitTargetOrientation><SitTargetPosition><X>0</X><Y>0</Y><Z>0</Z></SitTargetPosition><SitTargetPositionLL><X>0</X><Y>0</Y><Z>0</Z></SitTargetPositionLL><SitTargetOrientationLL><X>0</X><Y>0</Y><Z>0</Z><W>1</W></SitTargetOrientationLL><ParentID>1082081615</ParentID><CreationDate>1292715182</CreationDate><Category>0</Category><SalePrice>10</SalePrice><ObjectSaleType>0</ObjectSaleType><OwnershipCost>0</OwnershipCost><GroupID><Guid>00000000-0000-0000-0000-000000000000</Guid></GroupID><OwnerID><Guid>d5f1046f-7582-40e3-951c-b902143a2c9c</Guid></OwnerID><LastOwnerID><Guid>d5f1046f-7582-40e3-951c-b902143a2c9c</Guid></LastOwnerID><BaseMask>2147483647</BaseMask><OwnerMask>2147483647</OwnerMask><GroupMask>0</GroupMask><EveryoneMask>0</EveryoneMask><NextOwnerMask>2147483647</NextOwnerMask><Flags>Scripted Phantom</Flags><CollisionSound><Guid>00000000-0000-0000-0000-000000000000</Guid></CollisionSound><CollisionSoundVolume>0</CollisionSoundVolume></SceneObjectPart><SceneObjectPart xmlns:xsi="http://www.w3.org/2001/XMLSchema-instance" xmlns:xsd="http://www.w3.org/2001/XMLSchema"><AllowedDrop>false</AllowedDrop><CreatorID><Guid>d5f1046f-7582-40e3-951c-b902143a2c9c</Guid></CreatorID><FolderID><Guid>0a12946b-8a40-48a0-9dfa-bcb483711b71</Guid></FolderID><InventorySerial>0</InventorySerial><TaskInventory /><ObjectFlags>1088</ObjectFlags><UUID><Guid>0a12946b-8a40-48a0-9dfa-bcb483711b71</Guid></UUID><LocalId>1082081610</LocalId><Name>Primitive</Name><Material>3</Material><PassTouches>false</PassTouches><RegionHandle>11576757931588352</RegionHandle><ScriptAccessPin>0</ScriptAccessPin><PlaySoundSlavePrims /><LoopSoundSlavePrims /><GroupPosition><X>194.111954</X><Y>85.82587</Y><Z>61.5894661</Z></GroupPosition><OffsetPosition><X>0.704556763</X><Y>-1.39908648</Y><Z>-1.84424675</Z></OffsetPosition><RotationOffset><X>-0.474691331</X><Y>0.0781684443</Y><Z>-0.105321176</Z><W>-0.8703248</W></RotationOffset><Velocity><X>0</X><Y>0</Y><Z>0</Z></Velocity><AngularVelocity><X>0</X><Y>0</Y><Z>0</Z></AngularVelocity><Acceleration><X>0</X><Y>0</Y><Z>0</Z></Acceleration><Description /><Color /><Text /><SitName /><TouchName /><LinkNum>6</LinkNum><ClickAction>0</ClickAction><Shape><ProfileCurve>1</ProfileCurve><TextureEntry>ZFmkkrLWSzuwoLs/7GrGDBQLOj7sj9BFI5dQdmLWbRpWAAkcctsAmpmZPgCamZk+AAAAAAAAAAAAACAAAAAA</TextureEntry><ExtraParams>AA==</ExtraParams><PathBegin>0</PathBegin><PathCurve>16</PathCurve><PathEnd>0</PathEnd><PathRadiusOffset>0</PathRadiusOffset><PathRevolutions>0</PathRevolutions><PathScaleX>100</PathScaleX><PathScaleY>100</PathScaleY><PathShearX>0</PathShearX><PathShearY>0</PathShearY><PathSkew>0</PathSkew><PathTaperX>0</PathTaperX><PathTaperY>0</PathTaperY><PathTwist>0</PathTwist><PathTwistBegin>0</PathTwistBegin><PCode>9</PCode><ProfileBegin>0</ProfileBegin><ProfileEnd>0</ProfileEnd><ProfileHollow>0</ProfileHollow><Scale><X>0.5</X><Y>5.25640869</Y><Z>10</Z></Scale><State>0</State><ProfileShape>Square</ProfileShape><HollowShape>Same</HollowShape><SculptTexture><Guid>00000000-0000-0000-0000-000000000000</Guid></SculptTexture><SculptType>0</SculptType><SculptData /><FlexiSoftness>0</FlexiSoftness><FlexiTension>0</FlexiTension><FlexiDrag>0</FlexiDrag><FlexiGravity>0</FlexiGravity><FlexiWind>0</FlexiWind><FlexiForceX>0</FlexiForceX><FlexiForceY>0</FlexiForceY><FlexiForceZ>0</FlexiForceZ><LightColorR>0</LightColorR><LightColorG>0</LightColorG><LightColorB>0</LightColorB><LightColorA>1</LightColorA><LightRadius>0</LightRadius><LightCutoff>0</LightCutoff><LightFalloff>0</LightFalloff><LightIntensity>1</LightIntensity><FlexiEntry>false</FlexiEntry><LightEntry>false</LightEntry><SculptEntry>false</SculptEntry></Shape><Scale><X>0.5</X><Y>5.25640869</Y><Z>10</Z></Scale><UpdateFlag>0</UpdateFlag><SitTargetOrientation><X>0</X><Y>0</Y><Z>0</Z><W>1</W></SitTargetOrientation><SitTargetPosition><X>0</X><Y>0</Y><Z>0</Z></SitTargetPosition><SitTargetPositionLL><X>0</X><Y>0</Y><Z>0</Z></SitTargetPositionLL><SitTargetOrientationLL><X>0</X><Y>0</Y><Z>0</Z><W>1</W></SitTargetOrientationLL><ParentID>1082081615</ParentID><CreationDate>1292715182</CreationDate><Category>0</Category><SalePrice>10</SalePrice><ObjectSaleType>0</ObjectSaleType><OwnershipCost>0</OwnershipCost><GroupID><Guid>00000000-0000-0000-0000-000000000000</Guid></GroupID><OwnerID><Guid>d5f1046f-7582-40e3-951c-b902143a2c9c</Guid></OwnerID><LastOwnerID><Guid>d5f1046f-7582-40e3-951c-b902143a2c9c</Guid></LastOwnerID><BaseMask>2147483647</BaseMask><OwnerMask>2147483647</OwnerMask><GroupMask>0</GroupMask><EveryoneMask>0</EveryoneMask><NextOwnerMask>2147483647</NextOwnerMask><Flags>Scripted Phantom</Flags><CollisionSound><Guid>00000000-0000-0000-0000-000000000000</Guid></CollisionSound><CollisionSoundVolume>0</CollisionSoundVolume></SceneObjectPart><SceneObjectPart xmlns:xsi="http://www.w3.org/2001/XMLSchema-instance" xmlns:xsd="http://www.w3.org/2001/XMLSchema"><AllowedDrop>false</AllowedDrop><CreatorID><Guid>d5f1046f-7582-40e3-951c-b902143a2c9c</Guid></CreatorID><FolderID><Guid>2c232ed0-2413-4c65-92a0-e5420e47e02e</Guid></FolderID><InventorySerial>0</InventorySerial><TaskInventory /><ObjectFlags>1088</ObjectFlags><UUID><Guid>2c232ed0-2413-4c65-92a0-e5420e47e02e</Guid></UUID><LocalId>1082081611</LocalId><Name>Primitive</Name><Material>3</Material><PassTouches>false</PassTouches><RegionHandle>11576757931588352</RegionHandle><ScriptAccessPin>0</ScriptAccessPin><PlaySoundSlavePrims /><LoopSoundSlavePrims /><GroupPosition><X>194.111954</X><Y>85.82587</Y><Z>61.5894661</Z></GroupPosition><OffsetPosition><X>1.409401</X><Y>-0.380992234</Y><Z>-1.58495533</Z></OffsetPosition><RotationOffset><X>0.2516215</X><Y>0.05896069</Y><Z>0.1135515</Z><W>0.959331155</W></RotationOffset><Velocity><X>0</X><Y>0</Y><Z>0</Z></Velocity><AngularVelocity><X>0</X><Y>0</Y><Z>0</Z></AngularVelocity><Acceleration><X>0</X><Y>0</Y><Z>0</Z></Acceleration><Description /><Color /><Text /><SitName /><TouchName /><LinkNum>5</LinkNum><ClickAction>0</ClickAction><Shape><ProfileCurve>1</ProfileCurve><TextureEntry>ZFmkkrLWSzuwoLs/7GrGDBQLOj7sj9BFI5dQdmLWbRpWAAkcctsAmpmZPgCamZk+AAAAAAAAAAAAACAAAAAA</TextureEntry><ExtraParams>AA==</ExtraParams><PathBegin>0</PathBegin><PathCurve>16</PathCurve><PathEnd>0</PathEnd><PathRadiusOffset>0</PathRadiusOffset><PathRevolutions>0</PathRevolutions><PathScaleX>100</PathScaleX><PathScaleY>100</PathScaleY><PathShearX>0</PathShearX><PathShearY>0</PathShearY><PathSkew>0</PathSkew><PathTaperX>0</PathTaperX><PathTaperY>0</PathTaperY><PathTwist>0</PathTwist><PathTwistBegin>0</PathTwistBegin><PCode>9</PCode><ProfileBegin>0</ProfileBegin><ProfileEnd>0</ProfileEnd><ProfileHollow>0</ProfileHollow><Scale><X>0.5</X><Y>5.25640869</Y><Z>10</Z></Scale><State>0</State><ProfileShape>Square</ProfileShape><HollowShape>Same</HollowShape><SculptTexture><Guid>00000000-0000-0000-0000-000000000000</Guid></SculptTexture><SculptType>0</SculptType><SculptData /><FlexiSoftness>0</FlexiSoftness><FlexiTension>0</FlexiTension><FlexiDrag>0</FlexiDrag><FlexiGravity>0</FlexiGravity><FlexiWind>0</FlexiWind><FlexiForceX>0</FlexiForceX><FlexiForceY>0</FlexiForceY><FlexiForceZ>0</FlexiForceZ><LightColorR>0</LightColorR><LightColorG>0</LightColorG><LightColorB>0</LightColorB><LightColorA>1</LightColorA><LightRadius>0</LightRadius><LightCutoff>0</LightCutoff><LightFalloff>0</LightFalloff><LightIntensity>1</LightIntensity><FlexiEntry>false</FlexiEntry><LightEntry>false</LightEntry><SculptEntry>false</SculptEntry></Shape><Scale><X>0.5</X><Y>5.25640869</Y><Z>10</Z></Scale><UpdateFlag>0</UpdateFlag><SitTargetOrientation><X>0</X><Y>0</Y><Z>0</Z><W>1</W></SitTargetOrientation><SitTargetPosition><X>0</X><Y>0</Y><Z>0</Z></SitTargetPosition><SitTargetPositionLL><X>0</X><Y>0</Y><Z>0</Z></SitTargetPositionLL><SitTargetOrientationLL><X>0</X><Y>0</Y><Z>0</Z><W>1</W></SitTargetOrientationLL><ParentID>1082081615</ParentID><CreationDate>1292715182</CreationDate><Category>0</Category><SalePrice>10</SalePrice><ObjectSaleType>0</ObjectSaleType><OwnershipCost>0</OwnershipCost><GroupID><Guid>00000000-0000-0000-0000-000000000000</Guid></GroupID><OwnerID><Guid>d5f1046f-7582-40e3-951c-b902143a2c9c</Guid></OwnerID><LastOwnerID><Guid>d5f1046f-7582-40e3-951c-b902143a2c9c</Guid></LastOwnerID><BaseMask>2147483647</BaseMask><OwnerMask>2147483647</OwnerMask><GroupMask>0</GroupMask><EveryoneMask>0</EveryoneMask><NextOwnerMask>2147483647</NextOwnerMask><Flags>Scripted Phantom</Flags><CollisionSound><Guid>00000000-0000-0000-0000-000000000000</Guid></CollisionSound><CollisionSoundVolume>0</CollisionSoundVolume></SceneObjectPart><SceneObjectPart xmlns:xsi="http://www.w3.org/2001/XMLSchema-instance" xmlns:xsd="http://www.w3.org/2001/XMLSchema"><AllowedDrop>false</AllowedDrop><CreatorID><Guid>d5f1046f-7582-40e3-951c-b902143a2c9c</Guid></CreatorID><FolderID><Guid>44fe68a9-eaef-4cd0-9d83-0ab7196b54c7</Guid></FolderID><InventorySerial>0</InventorySerial><TaskInventory /><ObjectFlags>1088</ObjectFlags><UUID><Guid>44fe68a9-eaef-4cd0-9d83-0ab7196b54c7</Guid></UUID><LocalId>1082081612</LocalId><Name>Primitive</Name><Material>3</Material><PassTouches>false</PassTouches><RegionHandle>11576757931588352</RegionHandle><ScriptAccessPin>0</ScriptAccessPin><PlaySoundSlavePrims /><LoopSoundSlavePrims /><GroupPosition><X>194.111954</X><Y>85.82587</Y><Z>61.5894661</Z></GroupPosition><OffsetPosition><X>0.7572165</X><Y>-0.0172355119</Y><Z>-0.7450478</Z></OffsetPosition><RotationOffset><X>-0.0496483967</X><Y>0.0357123539</Y><Z>-0.632422</Z><W>0.772206</W></RotationOffset><Velocity><X>0</X><Y>0</Y><Z>0</Z></Velocity><AngularVelocity><X>0</X><Y>0</Y><Z>0</Z></AngularVelocity><Acceleration><X>0</X><Y>0</Y><Z>0</Z></Acceleration><Description /><Color /><Text /><SitName /><TouchName /><LinkNum>4</LinkNum><ClickAction>0</ClickAction><Shape><ProfileCurve>1</ProfileCurve><TextureEntry>ZFmkkrLWSzuwoLs/7GrGDBQLOj7sj9BFI5dQdmLWbRpWAAkcctsAmpmZPgCamZk+AAAAAAAAAAAAACAAAAAA</TextureEntry><ExtraParams>AA==</ExtraParams><PathBegin>0</PathBegin><PathCurve>16</PathCurve><PathEnd>0</PathEnd><PathRadiusOffset>0</PathRadiusOffset><PathRevolutions>0</PathRevolutions><PathScaleX>100</PathScaleX><PathScaleY>100</PathScaleY><PathShearX>0</PathShearX><PathShearY>0</PathShearY><PathSkew>0</PathSkew><PathTaperX>0</PathTaperX><PathTaperY>0</PathTaperY><PathTwist>0</PathTwist><PathTwistBegin>0</PathTwistBegin><PCode>9</PCode><ProfileBegin>0</ProfileBegin><ProfileEnd>0</ProfileEnd><ProfileHollow>0</ProfileHollow><Scale><X>0.5</X><Y>5.25640869</Y><Z>10</Z></Scale><State>0</State><ProfileShape>Square</ProfileShape><HollowShape>Same</HollowShape><SculptTexture><Guid>00000000-0000-0000-0000-000000000000</Guid></SculptTexture><SculptType>0</SculptType><SculptData /><FlexiSoftness>0</FlexiSoftness><FlexiTension>0</FlexiTension><FlexiDrag>0</FlexiDrag><FlexiGravity>0</FlexiGravity><FlexiWind>0</FlexiWind><FlexiForceX>0</FlexiForceX><FlexiForceY>0</FlexiForceY><FlexiForceZ>0</FlexiForceZ><LightColorR>0</LightColorR><LightColorG>0</LightColorG><LightColorB>0</LightColorB><LightColorA>1</LightColorA><LightRadius>0</LightRadius><LightCutoff>0</LightCutoff><LightFalloff>0</LightFalloff><LightIntensity>1</LightIntensity><FlexiEntry>false</FlexiEntry><LightEntry>false</LightEntry><SculptEntry>false</SculptEntry></Shape><Scale><X>0.5</X><Y>5.25640869</Y><Z>10</Z></Scale><UpdateFlag>0</UpdateFlag><SitTargetOrientation><X>0</X><Y>0</Y><Z>0</Z><W>1</W></SitTargetOrientation><SitTargetPosition><X>0</X><Y>0</Y><Z>0</Z></SitTargetPosition><SitTargetPositionLL><X>0</X><Y>0</Y><Z>0</Z></SitTargetPositionLL><SitTargetOrientationLL><X>0</X><Y>0</Y><Z>0</Z><W>1</W></SitTargetOrientationLL><ParentID>1082081615</ParentID><CreationDate>1292715182</CreationDate><Category>0</Category><SalePrice>10</SalePrice><ObjectSaleType>0</ObjectSaleType><OwnershipCost>0</OwnershipCost><GroupID><Guid>00000000-0000-0000-0000-000000000000</Guid></GroupID><OwnerID><Guid>d5f1046f-7582-40e3-951c-b902143a2c9c</Guid></OwnerID><LastOwnerID><Guid>d5f1046f-7582-40e3-951c-b902143a2c9c</Guid></LastOwnerID><BaseMask>2147483647</BaseMask><OwnerMask>2147483647</OwnerMask><GroupMask>0</GroupMask><EveryoneMask>0</EveryoneMask><NextOwnerMask>2147483647</NextOwnerMask><Flags>Scripted Phantom</Flags><CollisionSound><Guid>00000000-0000-0000-0000-000000000000</Guid></CollisionSound><CollisionSoundVolume>0</CollisionSoundVolume></SceneObjectPart><SceneObjectPart xmlns:xsi="http://www.w3.org/2001/XMLSchema-instance" xmlns:xsd="http://www.w3.org/2001/XMLSchema"><AllowedDrop>false</AllowedDrop><CreatorID><Guid>d5f1046f-7582-40e3-951c-b902143a2c9c</Guid></CreatorID><FolderID><Guid>5216aaac-56a1-4357-8f96-d2d8f1f758de</Guid></FolderID><InventorySerial>0</InventorySerial><TaskInventory /><ObjectFlags>1088</ObjectFlags><UUID><Guid>5216aaac-56a1-4357-8f96-d2d8f1f758de</Guid></UUID><LocalId>1082081613</LocalId><Name>Primitive</Name><Material>3</Material><PassTouches>false</PassTouches><RegionHandle>11576757931588352</RegionHandle><ScriptAccessPin>0</ScriptAccessPin><PlaySoundSlavePrims /><LoopSoundSlavePrims /><GroupPosition><X>194.111954</X><Y>85.82587</Y><Z>61.5894661</Z></GroupPosition><OffsetPosition><X>-1.762739</X><Y>0.265648752</Y><Z>-3.78558254</Z></OffsetPosition><RotationOffset><X>0.286860168</X><Y>-0.423961818</Y><Z>-0.0398927256</Z><W>0.85812366</W></RotationOffset><Velocity><X>0</X><Y>0</Y><Z>0</Z></Velocity><AngularVelocity><X>0</X><Y>0</Y><Z>0</Z></AngularVelocity><Acceleration><X>0</X><Y>0</Y><Z>0</Z></Acceleration><Description /><Color /><Text /><SitName /><TouchName /><LinkNum>3</LinkNum><ClickAction>0</ClickAction><Shape><ProfileCurve>0</ProfileCurve><TextureEntry>ZFmkkrLWSzuwoLs/7GrGDAAEBCzbADMzsz8AAABAQADNDAAAAAAAAAACAAAAAA==</TextureEntry><ExtraParams>AA==</ExtraParams><PathBegin>0</PathBegin><PathCurve>16</PathCurve><PathEnd>0</PathEnd><PathRadiusOffset>0</PathRadiusOffset><PathRevolutions>0</PathRevolutions><PathScaleX>100</PathScaleX><PathScaleY>100</PathScaleY><PathShearX>0</PathShearX><PathShearY>0</PathShearY><PathSkew>0</PathSkew><PathTaperX>0</PathTaperX><PathTaperY>0</PathTaperY><PathTwist>0</PathTwist><PathTwistBegin>0</PathTwistBegin><PCode>9</PCode><ProfileBegin>0</ProfileBegin><ProfileEnd>0</ProfileEnd><ProfileHollow>0</ProfileHollow><Scale><X>3</X><Y>3</Y><Z>6.539955</Z></Scale><State>0</State><ProfileShape>Circle</ProfileShape><HollowShape>Same</HollowShape><SculptTexture><Guid>00000000-0000-0000-0000-000000000000</Guid></SculptTexture><SculptType>0</SculptType><SculptData /><FlexiSoftness>0</FlexiSoftness><FlexiTension>0</FlexiTension><FlexiDrag>0</FlexiDrag><FlexiGravity>0</FlexiGravity><FlexiWind>0</FlexiWind><FlexiForceX>0</FlexiForceX><FlexiForceY>0</FlexiForceY><FlexiForceZ>0</FlexiForceZ><LightColorR>0</LightColorR><LightColorG>0</LightColorG><LightColorB>0</LightColorB><LightColorA>1</LightColorA><LightRadius>0</LightRadius><LightCutoff>0</LightCutoff><LightFalloff>0</LightFalloff><LightIntensity>1</LightIntensity><FlexiEntry>false</FlexiEntry><LightEntry>false</LightEntry><SculptEntry>false</SculptEntry></Shape><Scale><X>3</X><Y>3</Y><Z>6.539955</Z></Scale><UpdateFlag>0</UpdateFlag><SitTargetOrientation><X>0</X><Y>0</Y><Z>0</Z><W>1</W></SitTargetOrientation><SitTargetPosition><X>0</X><Y>0</Y><Z>0</Z></SitTargetPosition><SitTargetPositionLL><X>0</X><Y>0</Y><Z>0</Z></SitTargetPositionLL><SitTargetOrientationLL><X>0</X><Y>0</Y><Z>0</Z><W>1</W></SitTargetOrientationLL><ParentID>1082081615</ParentID><CreationDate>1292715183</CreationDate><Category>0</Category><SalePrice>10</SalePrice><ObjectSaleType>0</ObjectSaleType><OwnershipCost>0</OwnershipCost><GroupID><Guid>00000000-0000-0000-0000-000000000000</Guid></GroupID><OwnerID><Guid>d5f1046f-7582-40e3-951c-b902143a2c9c</Guid></OwnerID><LastOwnerID><Guid>d5f1046f-7582-40e3-951c-b902143a2c9c</Guid></LastOwnerID><BaseMask>2147483647</BaseMask><OwnerMask>2147483647</OwnerMask><GroupMask>0</GroupMask><EveryoneMask>0</EveryoneMask><NextOwnerMask>2147483647</NextOwnerMask><Flags>Scripted Phantom</Flags><CollisionSound><Guid>00000000-0000-0000-0000-000000000000</Guid></CollisionSound><CollisionSoundVolume>0</CollisionSoundVolume></SceneObjectPart><SceneObjectPart xmlns:xsi="http://www.w3.org/2001/XMLSchema-instance" xmlns:xsd="http://www.w3.org/2001/XMLSchema"><AllowedDrop>false</AllowedDrop><CreatorID><Guid>d5f1046f-7582-40e3-951c-b902143a2c9c</Guid></CreatorID><FolderID><Guid>7cdf092d-3818-49da-8c57-d31272dd188c</Guid></FolderID><InventorySerial>0</InventorySerial><TaskInventory /><ObjectFlags>1088</ObjectFlags><UUID><Guid>7cdf092d-3818-49da-8c57-d31272dd188c</Guid></UUID><LocalId>1082081614</LocalId><Name>Primitive</Name><Material>3</Material><PassTouches>false</PassTouches><RegionHandle>11576757931588352</RegionHandle><ScriptAccessPin>0</ScriptAccessPin><PlaySoundSlavePrims /><LoopSoundSlavePrims /><GroupPosition><X>194.111954</X><Y>85.82587</Y><Z>61.5894661</Z></GroupPosition><OffsetPosition><X>1.55414033</X><Y>-1.154627</Y><Z>-1.75227439</Z></OffsetPosition><RotationOffset><X>-0.475418836</X><Y>-0.076171115</Y><Z>-0.133381248</Z><W>-0.8662473</W></RotationOffset><Velocity><X>0</X><Y>0</Y><Z>0</Z></Velocity><AngularVelocity><X>0</X><Y>0</Y><Z>0</Z></AngularVelocity><Acceleration><X>0</X><Y>0</Y><Z>0</Z></Acceleration><Description /><Color /><Text /><SitName /><TouchName /><LinkNum>2</LinkNum><ClickAction>0</ClickAction><Shape><ProfileCurve>1</ProfileCurve><TextureEntry>ZFmkkrLWSzuwoLs/7GrGDBQLOj7sj9BFI5dQdmLWbRpWAAkcctsAmpmZPgCamZk+AAAAAAAAAAAAACAAAAAA</TextureEntry><ExtraParams>AA==</ExtraParams><PathBegin>0</PathBegin><PathCurve>16</PathCurve><PathEnd>0</PathEnd><PathRadiusOffset>0</PathRadiusOffset><PathRevolutions>0</PathRevolutions><PathScaleX>100</PathScaleX><PathScaleY>100</PathScaleY><PathShearX>0</PathShearX><PathShearY>0</PathShearY><PathSkew>0</PathSkew><PathTaperX>0</PathTaperX><PathTaperY>0</PathTaperY><PathTwist>0</PathTwist><PathTwistBegin>0</PathTwistBegin><PCode>9</PCode><ProfileBegin>0</ProfileBegin><ProfileEnd>0</ProfileEnd><ProfileHollow>0</ProfileHollow><Scale><X>0.5</X><Y>5.25640869</Y><Z>10</Z></Scale><State>0</State><ProfileShape>Square</ProfileShape><HollowShape>Same</HollowShape><SculptTexture><Guid>00000000-0000-0000-0000-000000000000</Guid></SculptTexture><SculptType>0</SculptType><SculptData /><FlexiSoftness>0</FlexiSoftness><FlexiTension>0</FlexiTension><FlexiDrag>0</FlexiDrag><FlexiGravity>0</FlexiGravity><FlexiWind>0</FlexiWind><FlexiForceX>0</FlexiForceX><FlexiForceY>0</FlexiForceY><FlexiForceZ>0</FlexiForceZ><LightColorR>0</LightColorR><LightColorG>0</LightColorG><LightColorB>0</LightColorB><LightColorA>1</LightColorA><LightRadius>0</LightRadius><LightCutoff>0</LightCutoff><LightFalloff>0</LightFalloff><LightIntensity>1</LightIntensity><FlexiEntry>false</FlexiEntry><LightEntry>false</LightEntry><SculptEntry>false</SculptEntry></Shape><Scale><X>0.5</X><Y>5.25640869</Y><Z>10</Z></Scale><UpdateFlag>0</UpdateFlag><SitTargetOrientation><X>0</X><Y>0</Y><Z>0</Z><W>1</W></SitTargetOrientation><SitTargetPosition><X>0</X><Y>0</Y><Z>0</Z></SitTargetPosition><SitTargetPositionLL><X>0</X><Y>0</Y><Z>0</Z></SitTargetPositionLL><SitTargetOrientationLL><X>0</X><Y>0</Y><Z>0</Z><W>1</W></SitTargetOrientationLL><ParentID>1082081615</ParentID><CreationDate>1292715183</CreationDate><Category>0</Category><SalePrice>10</SalePrice><ObjectSaleType>0</ObjectSaleType><OwnershipCost>0</OwnershipCost><GroupID><Guid>00000000-0000-0000-0000-000000000000</Guid></GroupID><OwnerID><Guid>d5f1046f-7582-40e3-951c-b902143a2c9c</Guid></OwnerID><LastOwnerID><Guid>d5f1046f-7582-40e3-951c-b902143a2c9c</Guid></LastOwnerID><BaseMask>2147483647</BaseMask><OwnerMask>2147483647</OwnerMask><GroupMask>0</GroupMask><EveryoneMask>0</EveryoneMask><NextOwnerMask>2147483647</NextOwnerMask><Flags>Scripted Phantom</Flags><CollisionSound><Guid>00000000-0000-0000-0000-000000000000</Guid></CollisionSound><CollisionSoundVolume>0</CollisionSoundVolume></SceneObjectPart></OtherParts></SceneObjectGroup>