<?xml version="1.0" encoding="utf-16"?>
<RegionSettings>
  <General>
    <AllowDamage>False</AllowDamage>
    <AllowLandResell>True</AllowLandResell>
    <AllowLandJoinDivide>True</AllowLandJoinDivide>
    <BlockFly>False</BlockFly>
    <BlockLandShowInSearch>False</BlockLandShowInSearch>
    <BlockTerraform>False</BlockTerraform>
    <DisableCollisions>False</DisableCollisions>
    <DisablePhysics>False</DisablePhysics>
    <DisableScripts>False</DisableScripts>
    <MaturityRating>1</MaturityRating>
    <RestrictPushing>False</RestrictPushing>
    <AgentLimit>40</AgentLimit>
    <ObjectBonus>1</ObjectBonus>
  </General>
  <GroundTextures>
    <Texture1>0958cb3b-6ba6-48c5-bfe4-09195b96fbf3</Texture1>
    <Texture2>99f77094-66c6-43e9-9009-d67b7a4881bd</Texture2>
    <Texture3>26ee1084-369c-4639-acfb-1cdabeb337c5</Texture3>
    <Texture4>3bd631ac-7e68-46e0-a4aa-903276e4abc9</Texture4>
    <ElevationLowSW>10</ElevationLowSW>
    <ElevationLowNW>10</ElevationLowNW>
    <ElevationLowSE>10</ElevationLowSE>
    <ElevationLowNE>10</ElevationLowNE>
    <ElevationHighSW>70</ElevationHighSW>
    <ElevationHighNW>70</ElevationHighNW>
    <ElevationHighSE>70</ElevationHighSE>
    <ElevationHighNE>70</ElevationHighNE>
  </GroundTextures>
  <Terrain>
    <WaterHeight>20</WaterHeight>
    <TerrainRaiseLimit>100</TerrainRaiseLimit>
    <TerrainLowerLimit>-100</TerrainLowerLimit>
    <UseEstateSun>True</UseEstateSun>
    <FixedSun>False</FixedSun>
  </Terrain>
</RegionSettings>